serial/__init__.py
serial/__main__.py
serial/rfc2217.py
serial/rs485.py
serial/serialcli.py
serial/serialjava.py
serial/serialposix.py
serial/serialutil.py
serial/serialwin32.py
serial/win32.py
serial/threaded/__init__.py
serial/tools/__init__.py
serial/tools/hexlify_codec.py
serial/tools/list_ports.py
serial/tools/list_ports_common.py
serial/tools/list_ports_linux.py
serial/tools/list_ports_osx.py
serial/tools/list_ports_posix.py
serial/tools/list_ports_windows.py
serial/tools/miniterm.py
serial/urlhandler/__init__.py
serial/urlhandler/protocol_alt.py
serial/urlhandler/protocol_cp2110.py
serial/urlhandler/protocol_hwgrep.py
serial/urlhandler/protocol_loop.py
serial/urlhandler/protocol_rfc2217.py
serial/urlhandler/protocol_socket.py
serial/urlhandler/protocol_spy.py
pyserial_labgrid-3.5.0.2.dist-info/LICENSE.txt
pyserial_labgrid-3.5.0.2.dist-info/METADATA
pyserial_labgrid-3.5.0.2.dist-info/WHEEL
pyserial_labgrid-3.5.0.2.dist-info/entry_points.txt
pyserial_labgrid-3.5.0.2.dist-info/top_level.txt
pyserial_labgrid-3.5.0.2.dist-info/RECORD
