Metadata-Version: 2.1
Name: pyserial-labgrid
Version: 3.5.0.2
Summary: Python Serial Port Extension (with labgrid RFC2217 fixes)
Author-email: Chris Liechti <cliechti@gmx.net>, Rouven Czerwinski <r.czerwinski@pengutronix.de>
License: BSD
Project-URL: Homepage, https://github.com/labgrid-project/pyserial-labgrid
Project-URL: Bug Tracker, https://github.com/labgrid-project/labgrid/issues
License-File: LICENSE.txt
Provides-Extra: cp2110
Requires-Dist: hidapi ; extra == 'cp2110'
